archicad/__init__.py
archicad/acbasetype.py
archicad/commands.py
archicad/connection.py
archicad/handlers.py
archicad/validators.py
archicad/versioning.py
archicad/releases/__init__.py
archicad/releases/ac24/__init__.py
archicad/releases/ac24/b2310commands.py
archicad/releases/ac24/b2310types.py
archicad/releases/ac24/b2310utilities.py
archicad/releases/ac24/b3000commands.py
archicad/releases/ac24/b3000types.py
archicad/releases/ac24/b3000utilities.py
archicad/releases/ac25/__init__.py
archicad/releases/ac25/b3000commands.py
archicad/releases/ac25/b3000types.py
archicad/releases/ac25/b3000utilities.py
archicad/releases/ac25/b326commands.py
archicad/releases/ac25/b326types.py
archicad/releases/ac25/b326utilities.py
archicad/releases/ac26/__init__.py
archicad/releases/ac26/b3005commands.py
archicad/releases/ac26/b3005types.py
archicad/releases/ac26/b3005utilities.py
archicad/releases/ac27/__init__.py
archicad/releases/ac27/b3001commands.py
archicad/releases/ac27/b3001types.py
archicad/releases/ac27/b3001utilities.py
archicad/releases/ac28/__init__.py
archicad/releases/ac28/b3001commands.py
archicad/releases/ac28/b3001types.py
archicad/releases/ac28/b3001utilities.py
archicad/releases/ac29/__init__.py
archicad/releases/ac29/b3000commands.py
archicad/releases/ac29/b3000types.py
archicad/releases/ac29/b3000utilities.py
archicad-29.3000.dist-info/LICENSE
archicad-29.3000.dist-info/METADATA
archicad-29.3000.dist-info/WHEEL
archicad-29.3000.dist-info/top_level.txt
archicad-29.3000.dist-info/RECORD
