Metadata-Version: 2.1
Name: archicad
Version: 29.3000
Summary: Python binding for the Archicad JSON command interface
Home-page: https://archicadapi.graphisoft.com/archicadPythonPackage/archicad.html
Author: Graphisoft SE
Author-email: archicadapi@graphisoft.com
License: Apache
Classifier: Programming Language :: Python :: 3
Classifier: License :: OSI Approved :: Apache Software License
Classifier: Operating System :: OS Independent
Requires-Python: >=3.7
License-File: LICENSE
